LICENSE
README.md
xini/__init__.py
xini/__main__.py
xini-0.2.2.dist-info/entry_points.txt
xini-0.2.2.dist-info/LICENSE
xini-0.2.2.dist-info/WHEEL
xini-0.2.2.dist-info/METADATA
xini-0.2.2.dist-info/RECORD
